{"frames": [

{
	"filename": "Hurt1 (Copy).png",
	"frame": {"x":0,"y":0,"w":800,"h":600},
	"rotated": false,
	"trimmed": false,
	"spriteSourceSize": {"x":0,"y":0,"w":800,"h":600},
	"sourceSize": {"w":800,"h":600},
	"pivot": {"x":0.5,"y":0.5}
},
{
	"filename": "Hurt2 (Copy).png",
	"frame": {"x":800,"y":0,"w":800,"h":600},
	"rotated": false,
	"trimmed": false,
	"spriteSourceSize": {"x":0,"y":0,"w":800,"h":600},
	"sourceSize": {"w":800,"h":600},
	"pivot": {"x":0.5,"y":0.5}
},
{
	"filename": "Hurt3 (Copy).png",
	"frame": {"x":1600,"y":0,"w":800,"h":600},
	"rotated": false,
	"trimmed": false,
	"spriteSourceSize": {"x":0,"y":0,"w":800,"h":600},
	"sourceSize": {"w":800,"h":600},
	"pivot": {"x":0.5,"y":0.5}
},
{
	"filename": "Hurt4 (Copy).png",
	"frame": {"x":2400,"y":0,"w":800,"h":600},
	"rotated": false,
	"trimmed": false,
	"spriteSourceSize": {"x":0,"y":0,"w":800,"h":600},
	"sourceSize": {"w":800,"h":600},
	"pivot": {"x":0.5,"y":0.5}
},
{
	"filename": "Hurt5 (Copy).png",
	"frame": {"x":3200,"y":0,"w":800,"h":600},
	"rotated": false,
	"trimmed": false,
	"spriteSourceSize": {"x":0,"y":0,"w":800,"h":600},
	"sourceSize": {"w":800,"h":600},
	"pivot": {"x":0.5,"y":0.5}
}],
"meta": {
	"app": "https://www.codeandweb.com/texturepacker",
	"version": "1.0",
	"image": "hurt.png",
	"format": "RGBA8888",
	"size": {"w":4000,"h":600},
	"scale": "1",
	"smartupdate": "$TexturePacker:SmartUpdate:bdcdfecf2e7726857a4b036593c8e2c1:2342c69a5ec1eb50378e1c20cd20fca8:9dda0143683f3b079bf6b30705451832$"
}
}
